codemirror/__init__.py
codemirror/widgets.py
django_codemirror-1.0.1.dist-info/LICENSE
django_codemirror-1.0.1.dist-info/METADATA
django_codemirror-1.0.1.dist-info/WHEEL
django_codemirror-1.0.1.dist-info/top_level.txt
django_codemirror-1.0.1.dist-info/RECORD
