Metadata-Version: 1.1
Name: django-codemirror
Version: 1.0.1
Summary: Django form widget for CodeMirror text editor
Home-page: https://github.com/onrik/django-codemirror
Author: Andrey
Author-email: and@rey.im
License: UNKNOWN
Platform: UNKNOWN
Classifier: Development Status :: 5 - Production/Stable
Classifier: Framework :: Django
Classifier: Intended Audience :: Developers
Classifier: Environment :: Web Environment
Classifier: Operating System :: OS Independent
Classifier: License :: OSI Approved :: MIT License
Classifier: Programming Language :: Python
Classifier: Programming Language :: Python :: 3
